[{"anime_id": 7482, "title": "Yume kara, Samenai", "cover": "https://cdn.myanimelist.net/images/anime/4/27220.jpg", "year": 80, "season": "All 80s", "themes": ["7482-00"], "__type__": "Anime"}, {"anime_id": 16954, "title": "Milky Passion: Dougenzaka - Ai no Shiro", "cover": "https://cdn.myanimelist.net/images/anime/11/45416.jpg", "year": 90, "season": "All 90s", "themes": ["16954-00"], "__type__": "Anime"}, {"anime_id": 9539, "title": "Cardfight!! Vanguard", "cover": "https://cdn.myanimelist.net/images/anime/11/41625.jpg", "year": "2011", "season": "Winter 2011", "themes": ["9539-00", "9539-01", "9539-02", "9539-03", "9539-04", "9539-05", "9539-06"], "__type__": "Anime"}, {"anime_id": 14373, "title": "Arata naru Sekai: World's/Start/Load/End | World's End", "cover": "https://cdn.myanimelist.net/images/anime/6/42075.jpg", "year": "2012", "season": "Fall 2012", "themes": ["14373-00"], "__type__": "Anime"}, {"anime_id": 13145, "title": "Cardfight!! Vanguard: Asia Circuit-hen | Cardfight!! Vanguard Asia Circuit", "cover": "https://cdn.myanimelist.net/images/anime/13/41627.jpg", "year": "2012", "season": "Spring 2012", "themes": ["13145-00", "13145-01", "13145-02", "13145-03"], "__type__": "Anime"}, {"anime_id": 15611, "title": "Cardfight!! Vanguard: Link Joker-hen | Cardfight!! Vanguard Link Joker", "cover": "https://cdn.myanimelist.net/images/anime/3/44566.jpg", "year": "2013", "season": "Winter 2013", "themes": ["15611-00", "15611-01", "15611-02", "15611-03", "15611-04", "15611-05", "15611-06"], "__type__": "Anime"}, {"anime_id": 23991, "title": "Cardfight!! Vanguard Movie: Neon Messiah", "cover": "https://cdn.myanimelist.net/images/anime/5/63797.jpg", "year": "2014", "season": "Fall 2014", "themes": ["23991-00", "23991-01"], "__type__": "Anime"}, {"anime_id": 21729, "title": "Cardfight!! Vanguard: Legion Mate-hen | Cardfight!! Vanguard Legion Mate", "cover": "https://cdn.myanimelist.net/images/anime/5/64773.jpg", "year": "2014", "season": "Spring 2014", "themes": ["21729-00", "21729-01", "21729-02", "21729-03"], "__type__": "Anime"}, {"anime_id": 31196, "title": "Cardfight!! Vanguard G: GIRS Crisis-hen | Cardfight!! Vanguard G GIRS Crisis", "cover": "https://cdn.myanimelist.net/images/anime/3/76231.jpg", "year": "2015", "season": "Fall 2015", "themes": ["31196-00", "31196-01"], "__type__": "Anime"}, {"anime_id": 34077, "title": "Cardfight!! Vanguard G: Next | Cardfight!! Vanguard G NEXT", "cover": "https://cdn.myanimelist.net/images/anime/13/82028.jpg", "year": "2016", "season": "Fall 2016", "themes": ["34077-00", "34077-01", "34077-02", "34077-03", "34077-04", "34077-05"], "__type__": "Anime"}, {"anime_id": 32802, "title": "Cardfight!! Vanguard G: Stride Gate-hen | Cardfight!! Vanguard G Stride Gate", "cover": "https://cdn.myanimelist.net/images/anime/10/80198.jpg", "year": "2016", "season": "Spring 2016", "themes": ["32802-00", "32802-01", "32802-02"], "__type__": "Anime"}, {"anime_id": 36022, "title": "Cardfight!! Vanguard G: Z | Cardfight!! Vanguard G Z", "cover": "https://cdn.myanimelist.net/images/anime/13/88063.jpg", "year": "2017", "season": "Fall 2017", "themes": ["36022-00", "36022-01"], "__type__": "Anime"}, {"anime_id": 40331, "title": "Ongaku | On-Gaku: Our Sound", "cover": "https://cdn.myanimelist.net/images/anime/1282/102835.jpg", "year": "2020", "season": "Winter 2020", "themes": ["40331-00"], "__type__": "Anime"}, {"anime_id": 37804, "title": "Shirobako Movie", "cover": "https://cdn.myanimelist.net/images/anime/1286/110725.jpg", "year": "2020", "season": "Winter 2020", "themes": ["37804-00", "37804-01"], "__type__": "Anime"}]